[
  {
    "blob_submitter": "Arbitrum One",
    "blobs": 2361,
    "time": "2024-06-17 00:00:00.000 UTC"
  },
  {
    "blob_submitter": "Base",
    "blobs": 5334,
    "time": "2024-06-17 00:00:00.000 UTC"
  },
  {
    "blob_submitter": "Lisk",
    "blobs": 13,
    "time": "2024-06-17 00:00:00.000 UTC"
  },
  {
    "blob_submitter": "BOB Network",
    "blobs": 37,
    "time": "2024-06-17 00:00:00.000 UTC"
  },
  {
    "blob_submitter": "Metal",
    "blobs": 358,
    "time": "2024-06-17 00:00:00.000 UTC"
  },
  {
    "blob_submitter": "Optopia",
    "blobs": 75,
    "time": "2024-06-17 00:00:00.000 UTC"
  },
  {
    "blob_submitter": "Lumio",
    "blobs": 8,
    "time": "2024-06-17 00:00:00.000 UTC"
  },
  {
    "blob_submitter": "Lambda",
    "blobs": 14,
    "time": "2024-06-17 00:00:00.000 UTC"
  },
  {
    "blob_submitter": "OP Mainnet",
    "blobs": 1595,
    "time": "2024-06-17 00:00:00.000 UTC"
  },
  {
    "blob_submitter": "Taiko",
    "blobs": 3307,
    "time": "2024-06-17 00:00:00.000 UTC"
  },
  {
    "blob_submitter": "Polynomial",
    "blobs": 8,
    "time": "2024-06-17 00:00:00.000 UTC"
  },
  {
    "blob_submitter": "Debank Chain",
    "blobs": 25,
    "time": "2024-06-17 00:00:00.000 UTC"
  },
  {
    "blob_submitter": "Scroll",
    "blobs": 1269,
    "time": "2024-06-17 00:00:00.000 UTC"
  },
  {
    "blob_submitter": "Boba Network",
    "blobs": 48,
    "time": "2024-06-17 00:00:00.000 UTC"
  }
]