[
  {
    "blob_submitter": "Mode",
    "blobs": 101,
    "time": "2024-04-01 00:00:00.000 UTC"
  },
  {
    "blob_submitter": "StarkNet",
    "blobs": 178,
    "time": "2024-04-01 00:00:00.000 UTC"
  },
  {
    "blob_submitter": "OP Mainnet",
    "blobs": 1860,
    "time": "2024-04-01 00:00:00.000 UTC"
  },
  {
    "blob_submitter": "Metal",
    "blobs": 12,
    "time": "2024-04-01 00:00:00.000 UTC"
  },
  {
    "blob_submitter": "Arbitrum One",
    "blobs": 1542,
    "time": "2024-04-01 00:00:00.000 UTC"
  },
  {
    "blob_submitter": "Inscriptions",
    "blobs": 10730,
    "time": "2024-04-01 00:00:00.000 UTC"
  },
  {
    "blob_submitter": "ZORA",
    "blobs": 170,
    "time": "2024-04-01 00:00:00.000 UTC"
  },
  {
    "blob_submitter": "zkSync Era",
    "blobs": 491,
    "time": "2024-04-01 00:00:00.000 UTC"
  },
  {
    "blob_submitter": "Base",
    "blobs": 2988,
    "time": "2024-04-01 00:00:00.000 UTC"
  },
  {
    "blob_submitter": "Linea",
    "blobs": 3211,
    "time": "2024-04-01 00:00:00.000 UTC"
  }
]