[
  {
    "blob_submitter": "zkSync Era",
    "blobs": 104,
    "time": "2024-08-10 00:00:00.000 UTC"
  },
  {
    "blob_submitter": "PandaSea",
    "blobs": 25,
    "time": "2024-08-10 00:00:00.000 UTC"
  },
  {
    "blob_submitter": "Paradex",
    "blobs": 346,
    "time": "2024-08-10 00:00:00.000 UTC"
  },
  {
    "blob_submitter": "Boba Network",
    "blobs": 48,
    "time": "2024-08-10 00:00:00.000 UTC"
  },
  {
    "blob_submitter": "Zircuit",
    "blobs": 491,
    "time": "2024-08-10 00:00:00.000 UTC"
  },
  {
    "blob_submitter": "Mint",
    "blobs": 36,
    "time": "2024-08-10 00:00:00.000 UTC"
  },
  {
    "blob_submitter": "Mode",
    "blobs": 80,
    "time": "2024-08-10 00:00:00.000 UTC"
  },
  {
    "blob_submitter": "Blast",
    "blobs": 1354,
    "time": "2024-08-10 00:00:00.000 UTC"
  },
  {
    "blob_submitter": "Shape",
    "blobs": 15,
    "time": "2024-08-10 00:00:00.000 UTC"
  },
  {
    "blob_submitter": "Kinto",
    "blobs": 6,
    "time": "2024-08-10 00:00:00.000 UTC"
  },
  {
    "blob_submitter": "Scroll",
    "blobs": 407,
    "time": "2024-08-10 00:00:00.000 UTC"
  },
  {
    "blob_submitter": "XGA",
    "blobs": 14,
    "time": "2024-08-10 00:00:00.000 UTC"
  },
  {
    "blob_submitter": "Kroma",
    "blobs": 180,
    "time": "2024-08-10 00:00:00.000 UTC"
  },
  {
    "blob_submitter": "Arbitrum One",
    "blobs": 1932,
    "time": "2024-08-10 00:00:00.000 UTC"
  },
  {
    "blob_submitter": "OP Mainnet",
    "blobs": 910,
    "time": "2024-08-10 00:00:00.000 UTC"
  },
  {
    "blob_submitter": "Lumio",
    "blobs": 16,
    "time": "2024-08-10 00:00:00.000 UTC"
  },
  {
    "blob_submitter": "Linea",
    "blobs": 297,
    "time": "2024-08-10 00:00:00.000 UTC"
  },
  {
    "blob_submitter": "RACE",
    "blobs": 77,
    "time": "2024-08-10 00:00:00.000 UTC"
  },
  {
    "blob_submitter": "River",
    "blobs": 184,
    "time": "2024-08-10 00:00:00.000 UTC"
  },
  {
    "blob_submitter": "World Chain",
    "blobs": 14,
    "time": "2024-08-10 00:00:00.000 UTC"
  },
  {
    "blob_submitter": "Lambda",
    "blobs": 14,
    "time": "2024-08-10 00:00:00.000 UTC"
  },
  {
    "blob_submitter": "Taiko",
    "blobs": 4243,
    "time": "2024-08-10 00:00:00.000 UTC"
  },
  {
    "blob_submitter": "Polynomial",
    "blobs": 17,
    "time": "2024-08-10 00:00:00.000 UTC"
  },
  {
    "blob_submitter": "Optopia",
    "blobs": 72,
    "time": "2024-08-10 00:00:00.000 UTC"
  },
  {
    "blob_submitter": "Swan Chain",
    "blobs": 11,
    "time": "2024-08-10 00:00:00.000 UTC"
  }
]