[
  {
    "blob_submitter": "World Chain",
    "blobs": 4710,
    "time": "2025-05-23 00:00:00.000 UTC"
  },
  {
    "blob_submitter": "pegglecoin",
    "blobs": 26,
    "time": "2025-05-23 00:00:00.000 UTC"
  },
  {
    "blob_submitter": "Infinaeon",
    "blobs": 9,
    "time": "2025-05-23 00:00:00.000 UTC"
  },
  {
    "blob_submitter": "Polynomial",
    "blobs": 42,
    "time": "2025-05-23 00:00:00.000 UTC"
  },
  {
    "blob_submitter": "HashKey",
    "blobs": 38,
    "time": "2025-05-23 00:00:00.000 UTC"
  },
  {
    "blob_submitter": "Linea",
    "blobs": 131,
    "time": "2025-05-23 00:00:00.000 UTC"
  },
  {
    "blob_submitter": "Superseed",
    "blobs": 25,
    "time": "2025-05-23 00:00:00.000 UTC"
  },
  {
    "blob_submitter": "BOB Network",
    "blobs": 23,
    "time": "2025-05-23 00:00:00.000 UTC"
  },
  {
    "blob_submitter": "Morph",
    "blobs": 72,
    "time": "2025-05-23 00:00:00.000 UTC"
  },
  {
    "blob_submitter": "Abstract",
    "blobs": 830,
    "time": "2025-05-23 00:00:00.000 UTC"
  },
  {
    "blob_submitter": "Swellchain",
    "blobs": 51,
    "time": "2025-05-23 00:00:00.000 UTC"
  },
  {
    "blob_submitter": "Mode",
    "blobs": 116,
    "time": "2025-05-23 00:00:00.000 UTC"
  },
  {
    "blob_submitter": "R0AR Chain",
    "blobs": 8,
    "time": "2025-05-23 00:00:00.000 UTC"
  },
  {
    "blob_submitter": "Unichain",
    "blobs": 1040,
    "time": "2025-05-23 00:00:00.000 UTC"
  },
  {
    "blob_submitter": "Boba Network",
    "blobs": 25,
    "time": "2025-05-23 00:00:00.000 UTC"
  },
  {
    "blob_submitter": "Shape",
    "blobs": 130,
    "time": "2025-05-23 00:00:00.000 UTC"
  },
  {
    "blob_submitter": "Arena-Z",
    "blobs": 4,
    "time": "2025-05-23 00:00:00.000 UTC"
  },
  {
    "blob_submitter": "Mint",
    "blobs": 57,
    "time": "2025-05-23 00:00:00.000 UTC"
  },
  {
    "blob_submitter": "Codex",
    "blobs": 16,
    "time": "2025-05-23 00:00:00.000 UTC"
  },
  {
    "blob_submitter": "Fuel",
    "blobs": 38,
    "time": "2025-05-23 00:00:00.000 UTC"
  },
  {
    "blob_submitter": "Settlus",
    "blobs": 16,
    "time": "2025-05-23 00:00:00.000 UTC"
  },
  {
    "blob_submitter": "Metis",
    "blobs": 91,
    "time": "2025-05-23 00:00:00.000 UTC"
  },
  {
    "blob_submitter": "Paradex",
    "blobs": 42,
    "time": "2025-05-23 00:00:00.000 UTC"
  },
  {
    "blob_submitter": "Arbitrum One",
    "blobs": 2724,
    "time": "2025-05-23 00:00:00.000 UTC"
  },
  {
    "blob_submitter": "Blast",
    "blobs": 414,
    "time": "2025-05-23 00:00:00.000 UTC"
  },
  {
    "blob_submitter": "Metal",
    "blobs": 359,
    "time": "2025-05-23 00:00:00.000 UTC"
  },
  {
    "blob_submitter": "Lighter",
    "blobs": 89,
    "time": "2025-05-23 00:00:00.000 UTC"
  },
  {
    "blob_submitter": "Debank Chain",
    "blobs": 21,
    "time": "2025-05-23 00:00:00.000 UTC"
  },
  {
    "blob_submitter": "ZORA",
    "blobs": 18,
    "time": "2025-05-23 00:00:00.000 UTC"
  },
  {
    "blob_submitter": "Hemi",
    "blobs": 86,
    "time": "2025-05-23 00:00:00.000 UTC"
  },
  {
    "blob_submitter": "Binary",
    "blobs": 8,
    "time": "2025-05-23 00:00:00.000 UTC"
  },
  {
    "blob_submitter": "StarkNet",
    "blobs": 168,
    "time": "2025-05-23 00:00:00.000 UTC"
  },
  {
    "blob_submitter": "Ethernity",
    "blobs": 5,
    "time": "2025-05-23 00:00:00.000 UTC"
  },
  {
    "blob_submitter": "Scroll",
    "blobs": 67,
    "time": "2025-05-23 00:00:00.000 UTC"
  },
  {
    "blob_submitter": "OP Mainnet",
    "blobs": 1411,
    "time": "2025-05-23 00:00:00.000 UTC"
  },
  {
    "blob_submitter": "Lisk",
    "blobs": 55,
    "time": "2025-05-23 00:00:00.000 UTC"
  }
]