[
  {
    "blob_submitter": "World Chain",
    "blobs": 2571,
    "time": "2025-02-10 00:00:00.000 UTC"
  },
  {
    "blob_submitter": "Superseed",
    "blobs": 16,
    "time": "2025-02-10 00:00:00.000 UTC"
  },
  {
    "blob_submitter": "HashKey",
    "blobs": 44,
    "time": "2025-02-10 00:00:00.000 UTC"
  },
  {
    "blob_submitter": "Swan Chain",
    "blobs": 7,
    "time": "2025-02-10 00:00:00.000 UTC"
  },
  {
    "blob_submitter": "zkSync Era",
    "blobs": 54,
    "time": "2025-02-10 00:00:00.000 UTC"
  },
  {
    "blob_submitter": "Shape",
    "blobs": 13,
    "time": "2025-02-10 00:00:00.000 UTC"
  },
  {
    "blob_submitter": "Paradex",
    "blobs": 147,
    "time": "2025-02-10 00:00:00.000 UTC"
  },
  {
    "blob_submitter": "Abstract",
    "blobs": 996,
    "time": "2025-02-10 00:00:00.000 UTC"
  },
  {
    "blob_submitter": "Morph",
    "blobs": 112,
    "time": "2025-02-10 00:00:00.000 UTC"
  },
  {
    "blob_submitter": "SNAXchain",
    "blobs": 16,
    "time": "2025-02-10 00:00:00.000 UTC"
  },
  {
    "blob_submitter": "pegglecoin",
    "blobs": 27,
    "time": "2025-02-10 00:00:00.000 UTC"
  },
  {
    "blob_submitter": "Lumio",
    "blobs": 16,
    "time": "2025-02-10 00:00:00.000 UTC"
  },
  {
    "blob_submitter": "Mint",
    "blobs": 292,
    "time": "2025-02-10 00:00:00.000 UTC"
  },
  {
    "blob_submitter": "Phala Network",
    "blobs": 75,
    "time": "2025-02-10 00:00:00.000 UTC"
  },
  {
    "blob_submitter": "Others",
    "blobs": 128,
    "time": "2025-02-10 00:00:00.000 UTC"
  },
  {
    "blob_submitter": "Taiko",
    "blobs": 3663,
    "time": "2025-02-10 00:00:00.000 UTC"
  },
  {
    "blob_submitter": "Polynomial",
    "blobs": 23,
    "time": "2025-02-10 00:00:00.000 UTC"
  },
  {
    "blob_submitter": "Optopia",
    "blobs": 8,
    "time": "2025-02-10 00:00:00.000 UTC"
  },
  {
    "blob_submitter": "OP Mainnet",
    "blobs": 920,
    "time": "2025-02-10 00:00:00.000 UTC"
  },
  {
    "blob_submitter": "Ethernity",
    "blobs": 5,
    "time": "2025-02-10 00:00:00.000 UTC"
  },
  {
    "blob_submitter": "ZERO Network",
    "blobs": 6,
    "time": "2025-02-10 00:00:00.000 UTC"
  },
  {
    "blob_submitter": "Linea",
    "blobs": 83,
    "time": "2025-02-10 00:00:00.000 UTC"
  },
  {
    "blob_submitter": "RACE",
    "blobs": 24,
    "time": "2025-02-10 00:00:00.000 UTC"
  },
  {
    "blob_submitter": "Lisk",
    "blobs": 512,
    "time": "2025-02-10 00:00:00.000 UTC"
  },
  {
    "blob_submitter": "River",
    "blobs": 90,
    "time": "2025-02-10 00:00:00.000 UTC"
  },
  {
    "blob_submitter": "Metal",
    "blobs": 358,
    "time": "2025-02-10 00:00:00.000 UTC"
  },
  {
    "blob_submitter": "StarkNet",
    "blobs": 53,
    "time": "2025-02-10 00:00:00.000 UTC"
  },
  {
    "blob_submitter": "Kroma",
    "blobs": 127,
    "time": "2025-02-10 00:00:00.000 UTC"
  },
  {
    "blob_submitter": "Debank Chain",
    "blobs": 15,
    "time": "2025-02-10 00:00:00.000 UTC"
  },
  {
    "blob_submitter": "Swell",
    "blobs": 26,
    "time": "2025-02-10 00:00:00.000 UTC"
  },
  {
    "blob_submitter": "Scroll",
    "blobs": 54,
    "time": "2025-02-10 00:00:00.000 UTC"
  },
  {
    "blob_submitter": "Fuel",
    "blobs": 140,
    "time": "2025-02-10 00:00:00.000 UTC"
  },
  {
    "blob_submitter": "Boba Network",
    "blobs": 25,
    "time": "2025-02-10 00:00:00.000 UTC"
  },
  {
    "blob_submitter": "Camp Network",
    "blobs": 25,
    "time": "2025-02-10 00:00:00.000 UTC"
  },
  {
    "blob_submitter": "R0AR Chain",
    "blobs": 9,
    "time": "2025-02-10 00:00:00.000 UTC"
  },
  {
    "blob_submitter": "Binary",
    "blobs": 61,
    "time": "2025-02-10 00:00:00.000 UTC"
  },
  {
    "blob_submitter": "Arena-Z",
    "blobs": 5,
    "time": "2025-02-10 00:00:00.000 UTC"
  },
  {
    "blob_submitter": "ZORA",
    "blobs": 30,
    "time": "2025-02-10 00:00:00.000 UTC"
  },
  {
    "blob_submitter": "Soneium",
    "blobs": 655,
    "time": "2025-02-10 00:00:00.000 UTC"
  },
  {
    "blob_submitter": "Mode",
    "blobs": 43,
    "time": "2025-02-10 00:00:00.000 UTC"
  },
  {
    "blob_submitter": "Blast",
    "blobs": 372,
    "time": "2025-02-10 00:00:00.000 UTC"
  },
  {
    "blob_submitter": "Lighter",
    "blobs": 28,
    "time": "2025-02-10 00:00:00.000 UTC"
  },
  {
    "blob_submitter": "Kinto",
    "blobs": 6,
    "time": "2025-02-10 00:00:00.000 UTC"
  },
  {
    "blob_submitter": "Infinaeon",
    "blobs": 8,
    "time": "2025-02-10 00:00:00.000 UTC"
  },
  {
    "blob_submitter": "Zircuit",
    "blobs": 102,
    "time": "2025-02-10 00:00:00.000 UTC"
  },
  {
    "blob_submitter": "Nal",
    "blobs": 25,
    "time": "2025-02-10 00:00:00.000 UTC"
  },
  {
    "blob_submitter": "Ink",
    "blobs": 128,
    "time": "2025-02-10 00:00:00.000 UTC"
  },
  {
    "blob_submitter": "Unichain",
    "blobs": 157,
    "time": "2025-02-10 00:00:00.000 UTC"
  },
  {
    "blob_submitter": "Base",
    "blobs": 7625,
    "time": "2025-02-10 00:00:00.000 UTC"
  }
]